Metadata-Version: 2.1
Name: jshbtf0302
Version: 4.4.0.dev0
Summary: State-of-the-art Natural Language Processing for TensorFlow 2.0 and PyTorch
Home-page: https://github.com/dust2002/test_0302_shb
Author: Thomas Wolf, Lysandre Debut, Victor Sanh, Julien Chaumond, Sam Shleifer, Patrick von Platen, Sylvain Gugger, Google AI Language Team Authors, Open AI team Authors, Facebook AI Authors, Carnegie Mellon University Authors
Author-email: thomas@huggingface.co
License: Apache
Keywords: NLP deep learning transformer pytorch tensorflow BERT GPT GPT-2 google openai CMU
Platform: UNKNOWN
Classifier: Development Status :: 5 - Production/Stable
Classifier: Intended Audience :: Developers
Classifier: Intended Audience :: Education
Classifier: Intended Audience :: Science/Research
Classifier: License :: OSI Approved :: Apache Software License
Classifier: Operating System :: OS Independent
Classifier: Programming Language :: Python :: 3
Classifier: Programming Language :: Python :: 3.6
Classifier: Programming Language :: Python :: 3.7
Classifier: Topic :: Scientific/Engineering :: Artificial Intelligence
Requires-Python: >=3.6.0
Requires-Dist: filelock
Requires-Dist: numpy (>=1.17)
Requires-Dist: packaging
Requires-Dist: regex (!=2019.12.17)
Requires-Dist: requests
Requires-Dist: sacremoses
Requires-Dist: tokenizers (<0.11,>=0.10.1)
Requires-Dist: tqdm (>=4.27)
Requires-Dist: dataclasses ; python_version < "3.7"
Requires-Dist: importlib-metadata ; python_version < "3.8"
Provides-Extra: all
Requires-Dist: tensorflow (>=2.3) ; extra == 'all'
Requires-Dist: onnxconverter-common ; extra == 'all'
Requires-Dist: keras2onnx ; extra == 'all'
Requires-Dist: torch (>=1.0) ; extra == 'all'
Requires-Dist: jax (>=0.2.8) ; extra == 'all'
Requires-Dist: jaxlib (>=0.1.59) ; extra == 'all'
Requires-Dist: flax (>=0.2.2) ; extra == 'all'
Requires-Dist: sentencepiece (==0.1.91) ; extra == 'all'
Requires-Dist: protobuf ; extra == 'all'
Requires-Dist: tokenizers (<0.11,>=0.10.1) ; extra == 'all'
Provides-Extra: dev
Requires-Dist: tensorflow (>=2.3) ; extra == 'dev'
Requires-Dist: onnxconverter-common ; extra == 'dev'
Requires-Dist: keras2onnx ; extra == 'dev'
Requires-Dist: torch (>=1.0) ; extra == 'dev'
Requires-Dist: jax (>=0.2.8) ; extra == 'dev'
Requires-Dist: jaxlib (>=0.1.59) ; extra == 'dev'
Requires-Dist: flax (>=0.2.2) ; extra == 'dev'
Requires-Dist: sentencepiece (==0.1.91) ; extra == 'dev'
Requires-Dist: protobuf ; extra == 'dev'
Requires-Dist: tokenizers (<0.11,>=0.10.1) ; extra == 'dev'
Requires-Dist: pytest ; extra == 'dev'
Requires-Dist: pytest-xdist ; extra == 'dev'
Requires-Dist: timeout-decorator ; extra == 'dev'
Requires-Dist: parameterized ; extra == 'dev'
Requires-Dist: psutil ; extra == 'dev'
Requires-Dist: datasets ; extra == 'dev'
Requires-Dist: faiss-cpu ; extra == 'dev'
Requires-Dist: cookiecutter (==1.7.2) ; extra == 'dev'
Requires-Dist: soundfile ; extra == 'dev'
Requires-Dist: black (>=20.8b1) ; extra == 'dev'
Requires-Dist: isort (>=5.5.4) ; extra == 'dev'
Requires-Dist: flake8 (>=3.8.3) ; extra == 'dev'
Requires-Dist: fugashi (>=1.0) ; extra == 'dev'
Requires-Dist: ipadic (<2.0,>=1.0.0) ; extra == 'dev'
Requires-Dist: unidic-lite (>=1.0.7) ; extra == 'dev'
Requires-Dist: unidic (>=1.0.2) ; extra == 'dev'
Requires-Dist: recommonmark ; extra == 'dev'
Requires-Dist: sphinx (==3.2.1) ; extra == 'dev'
Requires-Dist: sphinx-markdown-tables ; extra == 'dev'
Requires-Dist: sphinx-rtd-theme (==0.4.3) ; extra == 'dev'
Requires-Dist: sphinx-copybutton ; extra == 'dev'
Requires-Dist: scikit-learn ; extra == 'dev'
Provides-Extra: docs
Requires-Dist: recommonmark ; extra == 'docs'
Requires-Dist: sphinx (==3.2.1) ; extra == 'docs'
Requires-Dist: sphinx-markdown-tables ; extra == 'docs'
Requires-Dist: sphinx-rtd-theme (==0.4.3) ; extra == 'docs'
Requires-Dist: sphinx-copybutton ; extra == 'docs'
Provides-Extra: flax
Requires-Dist: jax (>=0.2.8) ; extra == 'flax'
Requires-Dist: jaxlib (>=0.1.59) ; extra == 'flax'
Requires-Dist: flax (>=0.2.2) ; extra == 'flax'
Provides-Extra: ja
Requires-Dist: fugashi (>=1.0) ; extra == 'ja'
Requires-Dist: ipadic (<2.0,>=1.0.0) ; extra == 'ja'
Requires-Dist: unidic-lite (>=1.0.7) ; extra == 'ja'
Requires-Dist: unidic (>=1.0.2) ; extra == 'ja'
Provides-Extra: modelcreation
Requires-Dist: cookiecutter (==1.7.2) ; extra == 'modelcreation'
Provides-Extra: onnxruntime
Requires-Dist: onnxruntime (>=1.4.0) ; extra == 'onnxruntime'
Requires-Dist: onnxruntime-tools (>=1.4.2) ; extra == 'onnxruntime'
Provides-Extra: quality
Requires-Dist: black (>=20.8b1) ; extra == 'quality'
Requires-Dist: isort (>=5.5.4) ; extra == 'quality'
Requires-Dist: flake8 (>=3.8.3) ; extra == 'quality'
Provides-Extra: retrieval
Requires-Dist: faiss-cpu ; extra == 'retrieval'
Requires-Dist: datasets ; extra == 'retrieval'
Provides-Extra: sentencepiece
Requires-Dist: sentencepiece (==0.1.91) ; extra == 'sentencepiece'
Requires-Dist: protobuf ; extra == 'sentencepiece'
Provides-Extra: serving
Requires-Dist: pydantic ; extra == 'serving'
Requires-Dist: uvicorn ; extra == 'serving'
Requires-Dist: fastapi ; extra == 'serving'
Requires-Dist: starlette ; extra == 'serving'
Provides-Extra: sklearn
Requires-Dist: scikit-learn ; extra == 'sklearn'
Provides-Extra: speech
Requires-Dist: soundfile ; extra == 'speech'
Provides-Extra: testing
Requires-Dist: pytest ; extra == 'testing'
Requires-Dist: pytest-xdist ; extra == 'testing'
Requires-Dist: timeout-decorator ; extra == 'testing'
Requires-Dist: parameterized ; extra == 'testing'
Requires-Dist: psutil ; extra == 'testing'
Requires-Dist: datasets ; extra == 'testing'
Requires-Dist: faiss-cpu ; extra == 'testing'
Requires-Dist: cookiecutter (==1.7.2) ; extra == 'testing'
Requires-Dist: soundfile ; extra == 'testing'
Provides-Extra: tf
Requires-Dist: tensorflow (>=2.3) ; extra == 'tf'
Requires-Dist: onnxconverter-common ; extra == 'tf'
Requires-Dist: keras2onnx ; extra == 'tf'
Provides-Extra: tf-cpu
Requires-Dist: tensorflow-cpu (>=2.3) ; extra == 'tf-cpu'
Requires-Dist: onnxconverter-common ; extra == 'tf-cpu'
Requires-Dist: keras2onnx ; extra == 'tf-cpu'
Provides-Extra: tokenizers
Requires-Dist: tokenizers (<0.11,>=0.10.1) ; extra == 'tokenizers'
Provides-Extra: torch
Requires-Dist: torch (>=1.0) ; extra == 'torch'
Provides-Extra: torchhub
Requires-Dist: filelock ; extra == 'torchhub'
Requires-Dist: importlib-metadata ; extra == 'torchhub'
Requires-Dist: numpy (>=1.17) ; extra == 'torchhub'
Requires-Dist: packaging ; extra == 'torchhub'
Requires-Dist: protobuf ; extra == 'torchhub'
Requires-Dist: regex (!=2019.12.17) ; extra == 'torchhub'
Requires-Dist: requests ; extra == 'torchhub'
Requires-Dist: sacremoses ; extra == 'torchhub'
Requires-Dist: sentencepiece (==0.1.91) ; extra == 'torchhub'
Requires-Dist: torch (>=1.0) ; extra == 'torchhub'
Requires-Dist: tokenizers (<0.11,>=0.10.1) ; extra == 'torchhub'
Requires-Dist: tqdm (>=4.27) ; extra == 'torchhub'
